simpl/__about__.py
simpl/__init__.py
simpl/chronos.py
simpl/cli.py
simpl/config.py
simpl/exceptions.py
simpl/git.py
simpl/log.py
simpl/rest.py
simpl/secrets.py
simpl/server.py
simpl/threadlocal.py
simpl/db/__init__.py
simpl/db/mongodb.py
simpl/incubator/__init__.py
simpl/incubator/dicts.py
simpl/incubator/rest.py
simpl/middleware/__init__.py
simpl/middleware/context.py
simpl/middleware/cors.py
simpl/middleware/errors.py
simpl/utils/__init__.py
simpl/utils/cli.py
simpl/utils/shell.py
simpl-1.1.0.dist-info/DESCRIPTION.rst
simpl-1.1.0.dist-info/METADATA
simpl-1.1.0.dist-info/RECORD
simpl-1.1.0.dist-info/WHEEL
simpl-1.1.0.dist-info/entry_points.txt
simpl-1.1.0.dist-info/metadata.json
simpl-1.1.0.dist-info/top_level.txt
tests/incubator/__init__.py
tests/incubator/test_rest.py
