Metadata-Version: 2.0
Name: simpl
Version: 1.1.0
Summary: simpl is a collection of useful, common python libraries, primarily for building web services and APIs
Home-page: https://github.com/checkmate/simpl
Author: Rackers
Author-email: samuel.stavinoha@rackspace.com
License: Apache License, Version 2.0
Keywords: common resuable suitable fruitful
Platform: UNKNOWN
Classifier: Intended Audience :: Developers
Classifier: License :: OSI Approved :: Apache Software License
Classifier: Operating System :: OS Independent
Classifier: Topic :: Software Development
Classifier: Programming Language :: Python
Classifier: Programming Language :: Python :: 2
Classifier: Programming Language :: Python :: 2.7
Classifier: Programming Language :: Python :: 3.4
Requires-Dist: six
